{
  "measuredAt": "2026-06-13T16:07:02.388Z",
  "symforgeBin": "C:\\AI_STUFF\\PROGRAMMING\\symforge\\target\\debug\\symforge.exe",
  "method": "ceil(bytes/4); M=competent_manual_window; facade relay via symforge _probe_*",
  "corpus": "pinned 20-row phase0-corpus (4 repos)",
  "surfaces": [
    {
      "surface": "full-32",
      "symforgeSurfaceEnv": "full",
      "toolCount": 32,
      "toolsListBytes": 62574,
      "h1Pass": false,
      "rowCount": 20,
      "session_net_accepted": 14389,
      "equiv_count": 20,
      "rows": [
        {
          "id": "cfg-if/t1_search",
          "surface": "full-32",
          "corpus": "cfg-if-rust",
          "tool": "search_text",
          "legacyTool": "search_text",
          "S": 194,
          "M": 1000,
          "sGteM": false,
          "responseBytes": 775,
          "acceptedServe": true,
          "equivalence": "EQUIVALENT",
          "goldenId": "cfg-if/t1_search",
          "decision": "serve",
          "mcpCalls": 1,
          "eligibleH6": true,
          "responseTextHash": 775
        },
        {
          "id": "cfg-if/t2_context",
          "surface": "full-32",
          "corpus": "cfg-if-rust",
          "tool": "get_file_context",
          "legacyTool": "get_file_context",
          "S": 154,
          "M": 1000,
          "sGteM": false,
          "responseBytes": 615,
          "acceptedServe": true,
          "equivalence": "EQUIVALENT",
          "goldenId": "cfg-if/t2_context",
          "decision": "serve",
          "mcpCalls": 1,
          "eligibleH6": true,
          "responseTextHash": 607
        },
        {
          "id": "cfg-if/t3_symbol",
          "surface": "full-32",
          "corpus": "cfg-if-rust",
          "tool": "search_symbols",
          "legacyTool": "search_symbols",
          "S": 76,
          "M": 1000,
          "sGteM": false,
          "responseBytes": 301,
          "acceptedServe": true,
          "equivalence": "EQUIVALENT",
          "goldenId": "cfg-if/t3_symbol",
          "decision": "serve",
          "mcpCalls": 1,
          "eligibleH6": true,
          "responseTextHash": 301
        },
        {
          "id": "cfg-if/t4_refs",
          "surface": "full-32",
          "corpus": "cfg-if-rust",
          "tool": "find_references",
          "legacyTool": "find_references",
          "S": 10,
          "M": 1000,
          "sGteM": false,
          "responseBytes": 38,
          "acceptedServe": true,
          "equivalence": "EQUIVALENT",
          "goldenId": "cfg-if/t4_refs",
          "decision": "serve",
          "mcpCalls": 1,
          "eligibleH6": true,
          "responseTextHash": 38
        },
        {
          "id": "cfg-if/t5_symbol",
          "surface": "full-32",
          "corpus": "cfg-if-rust",
          "tool": "get_symbol",
          "legacyTool": "get_symbol",
          "S": 302,
          "M": 1000,
          "sGteM": false,
          "responseBytes": 1208,
          "acceptedServe": true,
          "equivalence": "EQUIVALENT",
          "goldenId": "cfg-if/t5_symbol",
          "decision": "serve",
          "mcpCalls": 1,
          "eligibleH6": true,
          "responseTextHash": 1208
        },
        {
          "id": "records/t1_search",
          "surface": "full-32",
          "corpus": "records-python",
          "tool": "search_text",
          "legacyTool": "search_text",
          "S": 421,
          "M": 1000,
          "sGteM": false,
          "responseBytes": 1684,
          "acceptedServe": true,
          "equivalence": "EQUIVALENT",
          "goldenId": "records/t1_search",
          "decision": "serve",
          "mcpCalls": 1,
          "eligibleH6": true,
          "responseTextHash": 1674
        },
        {
          "id": "records/t2_context",
          "surface": "full-32",
          "corpus": "records-python",
          "tool": "get_file_context",
          "legacyTool": "get_file_context",
          "S": 671,
          "M": 1000,
          "sGteM": false,
          "responseBytes": 2684,
          "acceptedServe": true,
          "equivalence": "EQUIVALENT",
          "goldenId": "records/t2_context",
          "decision": "serve",
          "mcpCalls": 1,
          "eligibleH6": true,
          "responseTextHash": 2676
        },
        {
          "id": "records/t3_files",
          "surface": "full-32",
          "corpus": "records-python",
          "tool": "search_files",
          "legacyTool": "search_files",
          "S": 88,
          "M": 1000,
          "sGteM": false,
          "responseBytes": 350,
          "acceptedServe": true,
          "equivalence": "EQUIVALENT",
          "goldenId": "records/t3_files",
          "decision": "serve",
          "mcpCalls": 1,
          "eligibleH6": true,
          "responseTextHash": 342
        },
        {
          "id": "records/t4_refs",
          "surface": "full-32",
          "corpus": "records-python",
          "tool": "find_references",
          "legacyTool": "find_references",
          "S": 211,
          "M": 1000,
          "sGteM": false,
          "responseBytes": 841,
          "acceptedServe": true,
          "equivalence": "EQUIVALENT",
          "goldenId": "records/t4_refs",
          "decision": "serve",
          "mcpCalls": 1,
          "eligibleH6": true,
          "responseTextHash": 841
        },
        {
          "id": "records/t5_symbol",
          "surface": "full-32",
          "corpus": "records-python",
          "tool": "get_symbol",
          "legacyTool": "get_symbol",
          "S": 801,
          "M": 1000,
          "sGteM": false,
          "responseBytes": 3202,
          "acceptedServe": true,
          "equivalence": "EQUIVALENT",
          "goldenId": "records/t5_symbol",
          "decision": "serve",
          "mcpCalls": 1,
          "eligibleH6": true,
          "responseTextHash": 3202
        },
        {
          "id": "is-plain/t1_search",
          "surface": "full-32",
          "corpus": "is-plain-obj-ts",
          "tool": "search_text",
          "legacyTool": "search_text",
          "S": 384,
          "M": 1000,
          "sGteM": false,
          "responseBytes": 1536,
          "acceptedServe": true,
          "equivalence": "EQUIVALENT",
          "goldenId": "is-plain/t1_search",
          "decision": "serve",
          "mcpCalls": 1,
          "eligibleH6": true,
          "responseTextHash": 1536
        },
        {
          "id": "is-plain/t2_content",
          "surface": "full-32",
          "corpus": "is-plain-obj-ts",
          "tool": "get_file_content",
          "legacyTool": "get_file_content",
          "S": 86,
          "M": 800,
          "sGteM": false,
          "responseBytes": 343,
          "acceptedServe": true,
          "equivalence": "EQUIVALENT",
          "goldenId": "is-plain/t2_content",
          "decision": "serve",
          "mcpCalls": 1,
          "eligibleH6": true,
          "responseTextHash": 343
        },
        {
          "id": "is-plain/t3_context",
          "surface": "full-32",
          "corpus": "is-plain-obj-ts",
          "tool": "get_file_context",
          "legacyTool": "get_file_context",
          "S": 74,
          "M": 1000,
          "sGteM": false,
          "responseBytes": 296,
          "acceptedServe": true,
          "equivalence": "EQUIVALENT",
          "goldenId": "is-plain/t3_context",
          "decision": "serve",
          "mcpCalls": 1,
          "eligibleH6": true,
          "responseTextHash": 288
        },
        {
          "id": "is-plain/t4_symbols",
          "surface": "full-32",
          "corpus": "is-plain-obj-ts",
          "tool": "search_symbols",
          "legacyTool": "search_symbols",
          "S": 137,
          "M": 1000,
          "sGteM": false,
          "responseBytes": 548,
          "acceptedServe": true,
          "equivalence": "EQUIVALENT",
          "goldenId": "is-plain/t4_symbols",
          "decision": "serve",
          "mcpCalls": 1,
          "eligibleH6": true,
          "responseTextHash": 540
        },
        {
          "id": "is-plain/t5_symbol",
          "surface": "full-32",
          "corpus": "is-plain-obj-ts",
          "tool": "get_symbol",
          "legacyTool": "get_symbol",
          "S": 105,
          "M": 1000,
          "sGteM": false,
          "responseBytes": 419,
          "acceptedServe": true,
          "equivalence": "EQUIVALENT",
          "goldenId": "is-plain/t5_symbol",
          "decision": "serve",
          "mcpCalls": 1,
          "eligibleH6": true,
          "responseTextHash": 419
        },
        {
          "id": "compression/t1_search",
          "surface": "full-32",
          "corpus": "rust",
          "tool": "search_text",
          "legacyTool": "search_text",
          "S": 232,
          "M": 1000,
          "sGteM": false,
          "responseBytes": 927,
          "acceptedServe": true,
          "equivalence": "EQUIVALENT",
          "goldenId": "compression/t1_search",
          "decision": "serve",
          "mcpCalls": 1,
          "eligibleH6": true,
          "responseTextHash": 927
        },
        {
          "id": "compression/t2_context",
          "surface": "full-32",
          "corpus": "rust",
          "tool": "get_file_context",
          "legacyTool": "get_file_context",
          "S": 172,
          "M": 575,
          "sGteM": false,
          "responseBytes": 686,
          "acceptedServe": true,
          "equivalence": "EQUIVALENT",
          "goldenId": "compression/t2_context",
          "decision": "serve",
          "mcpCalls": 1,
          "eligibleH6": true,
          "responseTextHash": 678
        },
        {
          "id": "compression/t3_symbol",
          "surface": "full-32",
          "corpus": "rust",
          "tool": "get_symbol",
          "legacyTool": "get_symbol",
          "S": 396,
          "M": 575,
          "sGteM": false,
          "responseBytes": 1582,
          "acceptedServe": true,
          "equivalence": "EQUIVALENT",
          "goldenId": "compression/t3_symbol",
          "decision": "serve",
          "mcpCalls": 1,
          "eligibleH6": true,
          "responseTextHash": 1582
        },
        {
          "id": "compression/t4_refs",
          "surface": "full-32",
          "corpus": "rust",
          "tool": "find_references",
          "legacyTool": "find_references",
          "S": 11,
          "M": 1000,
          "sGteM": false,
          "responseBytes": 41,
          "acceptedServe": true,
          "equivalence": "EQUIVALENT",
          "goldenId": "compression/t4_refs",
          "decision": "serve",
          "mcpCalls": 1,
          "eligibleH6": true,
          "responseTextHash": 41
        },
        {
          "id": "compression/t5_dependents",
          "surface": "full-32",
          "corpus": "rust",
          "tool": "find_dependents",
          "legacyTool": "find_dependents",
          "S": 36,
          "M": 1000,
          "sGteM": false,
          "responseBytes": 141,
          "acceptedServe": true,
          "equivalence": "EQUIVALENT",
          "goldenId": "compression/t5_dependents",
          "decision": "serve",
          "mcpCalls": 1,
          "eligibleH6": true,
          "responseTextHash": 141
        }
      ]
    },
    {
      "surface": "compact-3",
      "symforgeSurfaceEnv": "compact",
      "toolCount": 3,
      "toolsListBytes": 891,
      "h1Pass": true,
      "rowCount": 20,
      "session_net_accepted": 14389,
      "equiv_count": 20,
      "rows": [
        {
          "id": "cfg-if/t1_search",
          "surface": "compact-3",
          "corpus": "cfg-if-rust",
          "tool": "symforge",
          "legacyTool": "search_text",
          "S": 194,
          "M": 1000,
          "sGteM": false,
          "responseBytes": 775,
          "acceptedServe": true,
          "equivalence": "EQUIVALENT",
          "goldenId": "cfg-if/t1_search",
          "decision": "serve",
          "mcpCalls": 1,
          "eligibleH6": true,
          "responseTextHash": 775
        },
        {
          "id": "cfg-if/t2_context",
          "surface": "compact-3",
          "corpus": "cfg-if-rust",
          "tool": "symforge",
          "legacyTool": "get_file_context",
          "S": 154,
          "M": 1000,
          "sGteM": false,
          "responseBytes": 615,
          "acceptedServe": true,
          "equivalence": "EQUIVALENT",
          "goldenId": "cfg-if/t2_context",
          "decision": "serve",
          "mcpCalls": 1,
          "eligibleH6": true,
          "responseTextHash": 607
        },
        {
          "id": "cfg-if/t3_symbol",
          "surface": "compact-3",
          "corpus": "cfg-if-rust",
          "tool": "symforge",
          "legacyTool": "search_symbols",
          "S": 76,
          "M": 1000,
          "sGteM": false,
          "responseBytes": 301,
          "acceptedServe": true,
          "equivalence": "EQUIVALENT",
          "goldenId": "cfg-if/t3_symbol",
          "decision": "serve",
          "mcpCalls": 1,
          "eligibleH6": true,
          "responseTextHash": 301
        },
        {
          "id": "cfg-if/t4_refs",
          "surface": "compact-3",
          "corpus": "cfg-if-rust",
          "tool": "symforge",
          "legacyTool": "find_references",
          "S": 10,
          "M": 1000,
          "sGteM": false,
          "responseBytes": 38,
          "acceptedServe": true,
          "equivalence": "EQUIVALENT",
          "goldenId": "cfg-if/t4_refs",
          "decision": "serve",
          "mcpCalls": 1,
          "eligibleH6": true,
          "responseTextHash": 38
        },
        {
          "id": "cfg-if/t5_symbol",
          "surface": "compact-3",
          "corpus": "cfg-if-rust",
          "tool": "symforge",
          "legacyTool": "get_symbol",
          "S": 302,
          "M": 1000,
          "sGteM": false,
          "responseBytes": 1208,
          "acceptedServe": true,
          "equivalence": "EQUIVALENT",
          "goldenId": "cfg-if/t5_symbol",
          "decision": "serve",
          "mcpCalls": 1,
          "eligibleH6": true,
          "responseTextHash": 1208
        },
        {
          "id": "records/t1_search",
          "surface": "compact-3",
          "corpus": "records-python",
          "tool": "symforge",
          "legacyTool": "search_text",
          "S": 421,
          "M": 1000,
          "sGteM": false,
          "responseBytes": 1684,
          "acceptedServe": true,
          "equivalence": "EQUIVALENT",
          "goldenId": "records/t1_search",
          "decision": "serve",
          "mcpCalls": 1,
          "eligibleH6": true,
          "responseTextHash": 1674
        },
        {
          "id": "records/t2_context",
          "surface": "compact-3",
          "corpus": "records-python",
          "tool": "symforge",
          "legacyTool": "get_file_context",
          "S": 671,
          "M": 1000,
          "sGteM": false,
          "responseBytes": 2684,
          "acceptedServe": true,
          "equivalence": "EQUIVALENT",
          "goldenId": "records/t2_context",
          "decision": "serve",
          "mcpCalls": 1,
          "eligibleH6": true,
          "responseTextHash": 2676
        },
        {
          "id": "records/t3_files",
          "surface": "compact-3",
          "corpus": "records-python",
          "tool": "symforge",
          "legacyTool": "search_files",
          "S": 88,
          "M": 1000,
          "sGteM": false,
          "responseBytes": 350,
          "acceptedServe": true,
          "equivalence": "EQUIVALENT",
          "goldenId": "records/t3_files",
          "decision": "serve",
          "mcpCalls": 1,
          "eligibleH6": true,
          "responseTextHash": 342
        },
        {
          "id": "records/t4_refs",
          "surface": "compact-3",
          "corpus": "records-python",
          "tool": "symforge",
          "legacyTool": "find_references",
          "S": 211,
          "M": 1000,
          "sGteM": false,
          "responseBytes": 841,
          "acceptedServe": true,
          "equivalence": "EQUIVALENT",
          "goldenId": "records/t4_refs",
          "decision": "serve",
          "mcpCalls": 1,
          "eligibleH6": true,
          "responseTextHash": 841
        },
        {
          "id": "records/t5_symbol",
          "surface": "compact-3",
          "corpus": "records-python",
          "tool": "symforge",
          "legacyTool": "get_symbol",
          "S": 801,
          "M": 1000,
          "sGteM": false,
          "responseBytes": 3202,
          "acceptedServe": true,
          "equivalence": "EQUIVALENT",
          "goldenId": "records/t5_symbol",
          "decision": "serve",
          "mcpCalls": 1,
          "eligibleH6": true,
          "responseTextHash": 3202
        },
        {
          "id": "is-plain/t1_search",
          "surface": "compact-3",
          "corpus": "is-plain-obj-ts",
          "tool": "symforge",
          "legacyTool": "search_text",
          "S": 384,
          "M": 1000,
          "sGteM": false,
          "responseBytes": 1536,
          "acceptedServe": true,
          "equivalence": "EQUIVALENT",
          "goldenId": "is-plain/t1_search",
          "decision": "serve",
          "mcpCalls": 1,
          "eligibleH6": true,
          "responseTextHash": 1536
        },
        {
          "id": "is-plain/t2_content",
          "surface": "compact-3",
          "corpus": "is-plain-obj-ts",
          "tool": "symforge",
          "legacyTool": "get_file_content",
          "S": 86,
          "M": 800,
          "sGteM": false,
          "responseBytes": 343,
          "acceptedServe": true,
          "equivalence": "EQUIVALENT",
          "goldenId": "is-plain/t2_content",
          "decision": "serve",
          "mcpCalls": 1,
          "eligibleH6": true,
          "responseTextHash": 343
        },
        {
          "id": "is-plain/t3_context",
          "surface": "compact-3",
          "corpus": "is-plain-obj-ts",
          "tool": "symforge",
          "legacyTool": "get_file_context",
          "S": 74,
          "M": 1000,
          "sGteM": false,
          "responseBytes": 296,
          "acceptedServe": true,
          "equivalence": "EQUIVALENT",
          "goldenId": "is-plain/t3_context",
          "decision": "serve",
          "mcpCalls": 1,
          "eligibleH6": true,
          "responseTextHash": 288
        },
        {
          "id": "is-plain/t4_symbols",
          "surface": "compact-3",
          "corpus": "is-plain-obj-ts",
          "tool": "symforge",
          "legacyTool": "search_symbols",
          "S": 137,
          "M": 1000,
          "sGteM": false,
          "responseBytes": 548,
          "acceptedServe": true,
          "equivalence": "EQUIVALENT",
          "goldenId": "is-plain/t4_symbols",
          "decision": "serve",
          "mcpCalls": 1,
          "eligibleH6": true,
          "responseTextHash": 540
        },
        {
          "id": "is-plain/t5_symbol",
          "surface": "compact-3",
          "corpus": "is-plain-obj-ts",
          "tool": "symforge",
          "legacyTool": "get_symbol",
          "S": 105,
          "M": 1000,
          "sGteM": false,
          "responseBytes": 419,
          "acceptedServe": true,
          "equivalence": "EQUIVALENT",
          "goldenId": "is-plain/t5_symbol",
          "decision": "serve",
          "mcpCalls": 1,
          "eligibleH6": true,
          "responseTextHash": 419
        },
        {
          "id": "compression/t1_search",
          "surface": "compact-3",
          "corpus": "rust",
          "tool": "symforge",
          "legacyTool": "search_text",
          "S": 232,
          "M": 1000,
          "sGteM": false,
          "responseBytes": 927,
          "acceptedServe": true,
          "equivalence": "EQUIVALENT",
          "goldenId": "compression/t1_search",
          "decision": "serve",
          "mcpCalls": 1,
          "eligibleH6": true,
          "responseTextHash": 927
        },
        {
          "id": "compression/t2_context",
          "surface": "compact-3",
          "corpus": "rust",
          "tool": "symforge",
          "legacyTool": "get_file_context",
          "S": 172,
          "M": 575,
          "sGteM": false,
          "responseBytes": 686,
          "acceptedServe": true,
          "equivalence": "EQUIVALENT",
          "goldenId": "compression/t2_context",
          "decision": "serve",
          "mcpCalls": 1,
          "eligibleH6": true,
          "responseTextHash": 678
        },
        {
          "id": "compression/t3_symbol",
          "surface": "compact-3",
          "corpus": "rust",
          "tool": "symforge",
          "legacyTool": "get_symbol",
          "S": 396,
          "M": 575,
          "sGteM": false,
          "responseBytes": 1582,
          "acceptedServe": true,
          "equivalence": "EQUIVALENT",
          "goldenId": "compression/t3_symbol",
          "decision": "serve",
          "mcpCalls": 1,
          "eligibleH6": true,
          "responseTextHash": 1582
        },
        {
          "id": "compression/t4_refs",
          "surface": "compact-3",
          "corpus": "rust",
          "tool": "symforge",
          "legacyTool": "find_references",
          "S": 11,
          "M": 1000,
          "sGteM": false,
          "responseBytes": 41,
          "acceptedServe": true,
          "equivalence": "EQUIVALENT",
          "goldenId": "compression/t4_refs",
          "decision": "serve",
          "mcpCalls": 1,
          "eligibleH6": true,
          "responseTextHash": 41
        },
        {
          "id": "compression/t5_dependents",
          "surface": "compact-3",
          "corpus": "rust",
          "tool": "symforge",
          "legacyTool": "find_dependents",
          "S": 36,
          "M": 1000,
          "sGteM": false,
          "responseBytes": 141,
          "acceptedServe": true,
          "equivalence": "EQUIVALENT",
          "goldenId": "compression/t5_dependents",
          "decision": "serve",
          "mcpCalls": 1,
          "eligibleH6": true,
          "responseTextHash": 141
        }
      ]
    },
    {
      "surface": "meta-1",
      "symforgeSurfaceEnv": "meta",
      "toolCount": 1,
      "toolsListBytes": 407,
      "h1Pass": true,
      "rowCount": 20,
      "session_net_accepted": 14389,
      "equiv_count": 20,
      "rows": [
        {
          "id": "cfg-if/t1_search",
          "surface": "meta-1",
          "corpus": "cfg-if-rust",
          "tool": "symforge",
          "legacyTool": "search_text",
          "S": 194,
          "M": 1000,
          "sGteM": false,
          "responseBytes": 775,
          "acceptedServe": true,
          "equivalence": "EQUIVALENT",
          "goldenId": "cfg-if/t1_search",
          "decision": "serve",
          "mcpCalls": 1,
          "eligibleH6": true,
          "responseTextHash": 775
        },
        {
          "id": "cfg-if/t2_context",
          "surface": "meta-1",
          "corpus": "cfg-if-rust",
          "tool": "symforge",
          "legacyTool": "get_file_context",
          "S": 154,
          "M": 1000,
          "sGteM": false,
          "responseBytes": 615,
          "acceptedServe": true,
          "equivalence": "EQUIVALENT",
          "goldenId": "cfg-if/t2_context",
          "decision": "serve",
          "mcpCalls": 1,
          "eligibleH6": true,
          "responseTextHash": 607
        },
        {
          "id": "cfg-if/t3_symbol",
          "surface": "meta-1",
          "corpus": "cfg-if-rust",
          "tool": "symforge",
          "legacyTool": "search_symbols",
          "S": 76,
          "M": 1000,
          "sGteM": false,
          "responseBytes": 301,
          "acceptedServe": true,
          "equivalence": "EQUIVALENT",
          "goldenId": "cfg-if/t3_symbol",
          "decision": "serve",
          "mcpCalls": 1,
          "eligibleH6": true,
          "responseTextHash": 301
        },
        {
          "id": "cfg-if/t4_refs",
          "surface": "meta-1",
          "corpus": "cfg-if-rust",
          "tool": "symforge",
          "legacyTool": "find_references",
          "S": 10,
          "M": 1000,
          "sGteM": false,
          "responseBytes": 38,
          "acceptedServe": true,
          "equivalence": "EQUIVALENT",
          "goldenId": "cfg-if/t4_refs",
          "decision": "serve",
          "mcpCalls": 1,
          "eligibleH6": true,
          "responseTextHash": 38
        },
        {
          "id": "cfg-if/t5_symbol",
          "surface": "meta-1",
          "corpus": "cfg-if-rust",
          "tool": "symforge",
          "legacyTool": "get_symbol",
          "S": 302,
          "M": 1000,
          "sGteM": false,
          "responseBytes": 1208,
          "acceptedServe": true,
          "equivalence": "EQUIVALENT",
          "goldenId": "cfg-if/t5_symbol",
          "decision": "serve",
          "mcpCalls": 1,
          "eligibleH6": true,
          "responseTextHash": 1208
        },
        {
          "id": "records/t1_search",
          "surface": "meta-1",
          "corpus": "records-python",
          "tool": "symforge",
          "legacyTool": "search_text",
          "S": 421,
          "M": 1000,
          "sGteM": false,
          "responseBytes": 1684,
          "acceptedServe": true,
          "equivalence": "EQUIVALENT",
          "goldenId": "records/t1_search",
          "decision": "serve",
          "mcpCalls": 1,
          "eligibleH6": true,
          "responseTextHash": 1674
        },
        {
          "id": "records/t2_context",
          "surface": "meta-1",
          "corpus": "records-python",
          "tool": "symforge",
          "legacyTool": "get_file_context",
          "S": 671,
          "M": 1000,
          "sGteM": false,
          "responseBytes": 2684,
          "acceptedServe": true,
          "equivalence": "EQUIVALENT",
          "goldenId": "records/t2_context",
          "decision": "serve",
          "mcpCalls": 1,
          "eligibleH6": true,
          "responseTextHash": 2676
        },
        {
          "id": "records/t3_files",
          "surface": "meta-1",
          "corpus": "records-python",
          "tool": "symforge",
          "legacyTool": "search_files",
          "S": 88,
          "M": 1000,
          "sGteM": false,
          "responseBytes": 350,
          "acceptedServe": true,
          "equivalence": "EQUIVALENT",
          "goldenId": "records/t3_files",
          "decision": "serve",
          "mcpCalls": 1,
          "eligibleH6": true,
          "responseTextHash": 342
        },
        {
          "id": "records/t4_refs",
          "surface": "meta-1",
          "corpus": "records-python",
          "tool": "symforge",
          "legacyTool": "find_references",
          "S": 211,
          "M": 1000,
          "sGteM": false,
          "responseBytes": 841,
          "acceptedServe": true,
          "equivalence": "EQUIVALENT",
          "goldenId": "records/t4_refs",
          "decision": "serve",
          "mcpCalls": 1,
          "eligibleH6": true,
          "responseTextHash": 841
        },
        {
          "id": "records/t5_symbol",
          "surface": "meta-1",
          "corpus": "records-python",
          "tool": "symforge",
          "legacyTool": "get_symbol",
          "S": 801,
          "M": 1000,
          "sGteM": false,
          "responseBytes": 3202,
          "acceptedServe": true,
          "equivalence": "EQUIVALENT",
          "goldenId": "records/t5_symbol",
          "decision": "serve",
          "mcpCalls": 1,
          "eligibleH6": true,
          "responseTextHash": 3202
        },
        {
          "id": "is-plain/t1_search",
          "surface": "meta-1",
          "corpus": "is-plain-obj-ts",
          "tool": "symforge",
          "legacyTool": "search_text",
          "S": 384,
          "M": 1000,
          "sGteM": false,
          "responseBytes": 1536,
          "acceptedServe": true,
          "equivalence": "EQUIVALENT",
          "goldenId": "is-plain/t1_search",
          "decision": "serve",
          "mcpCalls": 1,
          "eligibleH6": true,
          "responseTextHash": 1536
        },
        {
          "id": "is-plain/t2_content",
          "surface": "meta-1",
          "corpus": "is-plain-obj-ts",
          "tool": "symforge",
          "legacyTool": "get_file_content",
          "S": 86,
          "M": 800,
          "sGteM": false,
          "responseBytes": 343,
          "acceptedServe": true,
          "equivalence": "EQUIVALENT",
          "goldenId": "is-plain/t2_content",
          "decision": "serve",
          "mcpCalls": 1,
          "eligibleH6": true,
          "responseTextHash": 343
        },
        {
          "id": "is-plain/t3_context",
          "surface": "meta-1",
          "corpus": "is-plain-obj-ts",
          "tool": "symforge",
          "legacyTool": "get_file_context",
          "S": 74,
          "M": 1000,
          "sGteM": false,
          "responseBytes": 296,
          "acceptedServe": true,
          "equivalence": "EQUIVALENT",
          "goldenId": "is-plain/t3_context",
          "decision": "serve",
          "mcpCalls": 1,
          "eligibleH6": true,
          "responseTextHash": 288
        },
        {
          "id": "is-plain/t4_symbols",
          "surface": "meta-1",
          "corpus": "is-plain-obj-ts",
          "tool": "symforge",
          "legacyTool": "search_symbols",
          "S": 137,
          "M": 1000,
          "sGteM": false,
          "responseBytes": 548,
          "acceptedServe": true,
          "equivalence": "EQUIVALENT",
          "goldenId": "is-plain/t4_symbols",
          "decision": "serve",
          "mcpCalls": 1,
          "eligibleH6": true,
          "responseTextHash": 540
        },
        {
          "id": "is-plain/t5_symbol",
          "surface": "meta-1",
          "corpus": "is-plain-obj-ts",
          "tool": "symforge",
          "legacyTool": "get_symbol",
          "S": 105,
          "M": 1000,
          "sGteM": false,
          "responseBytes": 419,
          "acceptedServe": true,
          "equivalence": "EQUIVALENT",
          "goldenId": "is-plain/t5_symbol",
          "decision": "serve",
          "mcpCalls": 1,
          "eligibleH6": true,
          "responseTextHash": 419
        },
        {
          "id": "compression/t1_search",
          "surface": "meta-1",
          "corpus": "rust",
          "tool": "symforge",
          "legacyTool": "search_text",
          "S": 232,
          "M": 1000,
          "sGteM": false,
          "responseBytes": 927,
          "acceptedServe": true,
          "equivalence": "EQUIVALENT",
          "goldenId": "compression/t1_search",
          "decision": "serve",
          "mcpCalls": 1,
          "eligibleH6": true,
          "responseTextHash": 927
        },
        {
          "id": "compression/t2_context",
          "surface": "meta-1",
          "corpus": "rust",
          "tool": "symforge",
          "legacyTool": "get_file_context",
          "S": 172,
          "M": 575,
          "sGteM": false,
          "responseBytes": 686,
          "acceptedServe": true,
          "equivalence": "EQUIVALENT",
          "goldenId": "compression/t2_context",
          "decision": "serve",
          "mcpCalls": 1,
          "eligibleH6": true,
          "responseTextHash": 678
        },
        {
          "id": "compression/t3_symbol",
          "surface": "meta-1",
          "corpus": "rust",
          "tool": "symforge",
          "legacyTool": "get_symbol",
          "S": 396,
          "M": 575,
          "sGteM": false,
          "responseBytes": 1582,
          "acceptedServe": true,
          "equivalence": "EQUIVALENT",
          "goldenId": "compression/t3_symbol",
          "decision": "serve",
          "mcpCalls": 1,
          "eligibleH6": true,
          "responseTextHash": 1582
        },
        {
          "id": "compression/t4_refs",
          "surface": "meta-1",
          "corpus": "rust",
          "tool": "symforge",
          "legacyTool": "find_references",
          "S": 11,
          "M": 1000,
          "sGteM": false,
          "responseBytes": 41,
          "acceptedServe": true,
          "equivalence": "EQUIVALENT",
          "goldenId": "compression/t4_refs",
          "decision": "serve",
          "mcpCalls": 1,
          "eligibleH6": true,
          "responseTextHash": 41
        },
        {
          "id": "compression/t5_dependents",
          "surface": "meta-1",
          "corpus": "rust",
          "tool": "symforge",
          "legacyTool": "find_dependents",
          "S": 36,
          "M": 1000,
          "sGteM": false,
          "responseBytes": 141,
          "acceptedServe": true,
          "equivalence": "EQUIVALENT",
          "goldenId": "compression/t5_dependents",
          "decision": "serve",
          "mcpCalls": 1,
          "eligibleH6": true,
          "responseTextHash": 141
        }
      ]
    }
  ],
  "winner": {
    "selected": "compact-3",
    "tieBreak": "compact-3 (simpler per gap plan §4.1)",
    "criterion": "max session_net_accepted among H1-pass surfaces with output parity to full-32"
  }
}